metamask_institutional.sdk-0.6.2-py3.10-nspkg.pth
metamask_institutional/sdk/__init__.py
metamask_institutional/sdk/adapters/bitgo_adapter.py
metamask_institutional/sdk/adapters/bitgo_adapter_test.py
metamask_institutional/sdk/adapters/bitgo_create_tx_extra_params.py
metamask_institutional/sdk/adapters/cactus_adapter.py
metamask_institutional/sdk/adapters/cactus_adapter_test.py
metamask_institutional/sdk/adapters/cactus_create_tx_extra_params.py
metamask_institutional/sdk/adapters/jsonrpc_adapter.py
metamask_institutional/sdk/adapters/jsonrpc_adapter_test.py
metamask_institutional/sdk/adapters/qredo_adapter.py
metamask_institutional/sdk/adapters/qredo_adapter_test.py
metamask_institutional/sdk/adapters/qredo_create_tx_extra_params.py
metamask_institutional/sdk/bitgo/bitgo_client.py
metamask_institutional/sdk/bitgo/bitgo_client_test.py
metamask_institutional/sdk/bitgo/bitgo_create_tx_params.py
metamask_institutional/sdk/bitgo/bitgo_list_response.py
metamask_institutional/sdk/bitgo/bitgo_response.py
metamask_institutional/sdk/bitgo/bitgo_response_meta.py
metamask_institutional/sdk/bitgo/bitgo_transaction.py
metamask_institutional/sdk/cactus/cactus_client.py
metamask_institutional/sdk/cactus/cactus_client_test.py
metamask_institutional/sdk/cactus/cactus_get_transactions_params.py
metamask_institutional/sdk/cactus/cactus_transaction_detail.py
metamask_institutional/sdk/cactus/cactus_tx_params.py
metamask_institutional/sdk/cactus/custody-defi-api-4.yaml
metamask_institutional/sdk/common/__init__.py
metamask_institutional/sdk/common/abstract_client.py
metamask_institutional/sdk/common/base_model.py
metamask_institutional/sdk/common/custodian.py
metamask_institutional/sdk/common/dec_string.py
metamask_institutional/sdk/common/empty_string.py
metamask_institutional/sdk/common/ethereum_address.py
metamask_institutional/sdk/common/hex_string.py
metamask_institutional/sdk/common/transaction.py
metamask_institutional/sdk/common/transaction_params.py
metamask_institutional.sdk-0.6.2.dist-info/LICENSE
metamask_institutional.sdk-0.6.2.dist-info/METADATA
metamask_institutional.sdk-0.6.2.dist-info/WHEEL
metamask_institutional.sdk-0.6.2.dist-info/namespace_packages.txt
metamask_institutional.sdk-0.6.2.dist-info/top_level.txt
metamask_institutional.sdk-0.6.2.dist-info/RECORD
